<annotation>
	<folder>Annotations</folder>
	<filename>i127.JPG</filename>
	<path>C:\Users\KD823ER\Desktop\images\darkflow-master\train\Annotations\i127.JPG</path>
	<source>
		<database>Unknown</database>
	</source>
	<size>
		<width>484</width>
		<height>1280</height>
		<depth>3</depth>
	</size>
	<segmented>0</segmented>
	<object>
		<name>barcode</name>
		<pose>Unspecified</pose>
		<truncated>0</truncated>
		<difficult>0</difficult>
		<bndbox>
			<xmin>60</xmin>
			<ymin>768</ymin>
			<xmax>180</xmax>
			<ymax>1019</ymax>
		</bndbox>
	</object>
</annotation>
